{"consecutivo":"276","clave":{"sucursal":"1","terminal":"1","tipo_comprobante":"1","situacion_comprobante":"1"},"encabezado":{"condicion_venta":"2","plazo_credito":"60","medio_pago":["4"]},"receptor":{"nombre":"Mondelez Costa Rica Ltda","identificacion":{"tipo":"2","numero":"3102149900"},"correo_electronico":"FacturaselectronicaCR@Mdlz.com"},"detalle":[{"codigo":[{"tipo":"4","codigo":"5"}],"cantidad":"1.000","unidad_medida":"Sp","unidad_medida_comercial":"Sp","detalle":"Servicio de administración de personal Setiembre-2018 Scientist Affairs Heyleen Chin","precio_unitario":"2821867.38000","monto_total":"2821867.38000","monto_descuento":0,"naturaleza_descuento":"No Aplica","subtotal":"2821867.38000","monto_total_linea":"2821867.38000"}],"resumen":{"moneda":"CRC","tipo_cambio":"1.00000","total_servicios_gravados":"0.00000","total_servicios_exentos":"2821867.38000","total_mercancias_gravadas":"0.00000","total_mercancias_exentas":"0.00000","total_gravado":"0.00000","total_exento":"2821867.38000","total_venta":"2821867.38000","total_descuentos":"0.00000","total_venta_neta":"2821867.38000","total_impuesto":"0.00000","total_comprobante":"2821867.38000"},"otros":[{"codigo":"memo","otro_texto":"Servicios Setiembre"}]}